BasicBand/__init__.py
BasicBand/basicband.py
BasicBand-0.1.dist-info/METADATA
BasicBand-0.1.dist-info/WHEEL
BasicBand-0.1.dist-info/top_level.txt
BasicBand-0.1.dist-info/RECORD
