Metadata-Version: 2.1
Name: BasicBand
Version: 0.1
Summary: BasicBand Dataset 
Home-page: UNKNOWN
Author: Juan Montesinos
Author-email: juanfelipe.montesinos@upf.edu
License: UNKNOWN
Platform: UNKNOWN
Classifier: Programming Language :: Python :: 3
